odoo/addons/l10n_th_partner/README.rst
odoo/addons/l10n_th_partner/__init__.py
odoo/addons/l10n_th_partner/__manifest__.py
odoo/addons/l10n_th_partner/hooks.py
odoo/addons/l10n_th_partner/data/res.partner.company.type.csv
odoo/addons/l10n_th_partner/data/res.partner.title.csv
odoo/addons/l10n_th_partner/i18n/l10n_th_partner.pot
odoo/addons/l10n_th_partner/i18n/th.po
odoo/addons/l10n_th_partner/models/__init__.py
odoo/addons/l10n_th_partner/models/res_company.py
odoo/addons/l10n_th_partner/models/res_partner.py
odoo/addons/l10n_th_partner/models/res_partner_company_type.py
odoo/addons/l10n_th_partner/models/res_users.py
odoo/addons/l10n_th_partner/readme/CONTRIBUTORS.rst
odoo/addons/l10n_th_partner/readme/DESCRIPTION.rst
odoo/addons/l10n_th_partner/readme/HISTORY.rst
odoo/addons/l10n_th_partner/static/description/icon.png
odoo/addons/l10n_th_partner/static/description/index.html
odoo/addons/l10n_th_partner/tests/__init__.py
odoo/addons/l10n_th_partner/tests/test_l10n_th_partner.py
odoo/addons/l10n_th_partner/views/res_company_view.xml
odoo/addons/l10n_th_partner/views/res_partner_company_type_view.xml
odoo/addons/l10n_th_partner/views/res_partner_view.xml
odoo/addons/l10n_th_partner/views/res_users_view.xml
odoo13_addon_l10n_th_partner-13.0.1.2.1.dist-info/METADATA
odoo13_addon_l10n_th_partner-13.0.1.2.1.dist-info/WHEEL
odoo13_addon_l10n_th_partner-13.0.1.2.1.dist-info/top_level.txt
odoo13_addon_l10n_th_partner-13.0.1.2.1.dist-info/RECORD
